ftdiapp/__init__.py
ftdiapp/ftdispi.py
ftdiapp/nand_flash_devices.py
ftdiapp/nor_flash_devices.py
ftdiapp-0.0.2.dist-info/LICENSE
ftdiapp-0.0.2.dist-info/METADATA
ftdiapp-0.0.2.dist-info/WHEEL
ftdiapp-0.0.2.dist-info/top_level.txt
ftdiapp-0.0.2.dist-info/RECORD
